acdh_tei_pyutils/__init__.py
acdh_tei_pyutils/cli.py
acdh_tei_pyutils/tei.py
acdh_tei_pyutils/utils.py
acdh_tei_pyutils/files/clean_markup.xsl
acdh_tei_pyutils/files/tei.xml
acdh_tei_pyutils/files/tei_no_id.xml
acdh_tei_pyutils/files/tei_no_ids.xml
acdh_tei_pyutils/files/tei_trailing_slash.xml
acdh_tei_pyutils-29.1.dist-info/LICENSE
acdh_tei_pyutils-29.1.dist-info/METADATA
acdh_tei_pyutils-29.1.dist-info/WHEEL
acdh_tei_pyutils-29.1.dist-info/entry_points.txt
acdh_tei_pyutils-29.1.dist-info/top_level.txt
acdh_tei_pyutils-29.1.dist-info/RECORD
