Metadata-Version: 2.1
Name: acdh-tei-pyutils
Version: 29.1
Summary: Utilty functions to work with TEI Documents
Home-page: https://github.com/acdh-oeaw/acdh-tei-pyutils
Author: Peter Andorfer, Daniel Stoxreiter
Author-email: peter.andorfer@oeaw.ac.at
License: MIT
Keywords: acdh-tei-pyutils
Classifier: Development Status :: 2 - Pre-Alpha
Classifier: Intended Audience :: Developers
Classifier: License :: OSI Approved :: MIT License
Classifier: Natural Language :: English
Classifier: Programming Language :: Python :: 3
Classifier: Programming Language :: Python :: 3.7
Classifier: Programming Language :: Python :: 3.8
Requires-Python: >=3.7
License-File: LICENSE
Requires-Dist: acdh-xml-pyutils
Requires-Dist: acdh-handle-pyutils (<4,>=0.3.0)
Requires-Dist: click (>=7.1.2)
Requires-Dist: tqdm (>=4.59.0)
